marat/__init__.py
marat/__main__.py
marat/bots/__init__.py
marat/bots/telegram_bot.py
marat/bots/worker.py
marat/migrations/marat1.py
marat/roles/member.py
marat/roles/user.py
marat/token/currency.py
marat/token/nft.py
marat/token/token.py
marat/token/tokens_bag.py
marat/token/transaction.py
marat/token/transaction_batch.py
marat/token/wallet.py
marat-0.1.0.dist-info/METADATA
marat-0.1.0.dist-info/WHEEL
marat-0.1.0.dist-info/RECORD
