Metadata-Version: 2.3
Name: marat
Version: 0.1.0
Summary: 
Author: Nikita Umerov
Author-email: nagvalhm@yandex.ru
Requires-Python: >=3.10,<4.0
Classifier: Programming Language :: Python :: 3
Classifier: Programming Language :: Python :: 3.10
Classifier: Programming Language :: Python :: 3.11
Classifier: Programming Language :: Python :: 3.12
Classifier: Programming Language :: Python :: 3.13
Requires-Dist: aiogram (>=3.20.0.post0,<4.0.0)
Requires-Dist: epure (>=0.3.12,<0.4.0)
Project-URL: Homepage, https://github.com/nagvalhm/marat
Project-URL: Source, https://github.com/nagvalhm/marat
